{"startingBalance":162113,"transactions":[{"tranid":"ad8aeded-0bbd-4bf0-a6d2-9441c8800faf","description":"Walgreens","date":"2013-07-26","amount":"3207","type":"Debit","cleared":true,"category":"Doctor Bills"},{"tranid":"1d6b1b99-693a-43b2-b28a-eb839bc40caf","description":"Walgreens","date":"2013-07-26","amount":"1000","type":"Debit","cleared":true,"category":"Doctor Bills"},{"tranid":"e3784959-730b-4c7a-81ea-2aec301f4186","description":"Amazon","date":"2013-07-26","amount":"1050","type":"Debit","cleared":true,"category":"Suppliments"},{"tranid":"3460179a-22c7-4a08-9dee-91b902dc7ad1","description":"Envelopes","date":"2013-07-26","amount":"80000","type":"Debit","cleared":true,"category":"Split","categories":[{"category":"Groceries","amount":"55000"},{"category":"Gas & Fuel","amount":"11500"},{"category":"Kid's Earnings","amount":"1500"},{"category":"County Fair","amount":"12000"}]},{"tranid":"3392c63c-5635-40fe-a3d2-1e0fd423192e","description":"State Farm Paycheck","date":"2013-07-26","amount":"302546","type":"Credit","cleared":true,"category":"1st Paycheck"},{"tranid":"8e26eb9a-5ff1-42e1-bbf4-70e0559690d4","description":"Starved Rock Lodge","date":"2013-07-27","amount":"1832","type":"Debit","cleared":true,"category":"Eating Out"},{"tranid":"5c698b86-8e7e-43ba-9210-c0a3cf1d81c8","description":"State Farm Paycheck","date":"2013-07-29","amount":"10000","type":"Credit","cleared":true,"category":"Bonus"},{"tranid":"40383334-b100-40a8-b328-dd1fb57cd820","description":"Schwan's","date":"2013-07-26","amount":"6400","type":"Debit","cleared":true,"category":"Schwan's"},{"tranid":"a17ab289-301a-4958-a6a9-dcbb37d13d04","description":"Amazon","date":"2013-08-01","amount":"3155","type":"Debit","cleared":true,"category":"Suppliments"},{"tranid":"f9fceb10-2f34-497d-ae32-3cef25acfe0b","description":"Trek home educators","date":"2013-08-01","amount":"11500","type":"Debit","cleared":true,"category":"Subscriptions"},{"tranid":"ade8de38-b156-46c1-98b9-a6bf4eff3ec8","description":"Meatheads (Normal)","date":"2013-08-01","amount":"2744","type":"Debit","cleared":true,"category":"Eating Out"},{"tranid":"e317ccdc-1ade-46cc-93db-3df98d260a02","description":"Amazon","date":"2013-08-01","amount":"1799","type":"Debit","cleared":true,"category":"Suppliments"},{"tranid":"507f6e6c-6d71-4db6-a984-be00eda1c182","description":"Target","date":"2013-08-01","amount":"1237","type":"Debit","cleared":true,"category":"Books and Supplies"},{"tranid":"6192c619-40bd-4067-a579-4705f83c1d52","description":"Amazon","date":"2013-08-01","amount":"2868","type":"Debit","cleared":true,"category":"Suppliments"},{"tranid":"c67861e7-a2df-4578-b7c1-524822547946","description":"PNC Mortgage","date":"2013-08-01","amount":"136216","type":"Debit","cleared":true,"category":"Mortgage"},{"tranid":"9f51d19c-6d1d-4fea-ba36-9eda74da1020","description":"Mojang","date":"2013-08-01","amount":"2695","type":"Debit","cleared":true,"category":"Paul - Fun Money"},{"tranid":"152b49d3-6066-479d-b0fb-7d1949d15b90","description":"Foreign Transaction","date":"2013-08-01","amount":"81","type":"Debit","cleared":true,"category":"Paul - Fun Money"},{"tranid":"48444d5e-f7e8-456e-8ef2-13a33c755dac","description":"ATM Deposit","date":"2013-08-02","amount":6500,"type":"Credit","cleared":true,"category":"Gas & Fuel"},{"tranid":"6e8760d3-02d0-4014-9e05-ef973a251028","description":"Qik 'N Ez","date":"2013-08-02","amount":"3000","type":"Debit","cleared":true,"category":"Gas & Fuel"},{"tranid":"a1f90685-3b7c-4e3b-a212-6cdc8d320993","description":"Hucks","date":"2013-08-02","amount":"5483","type":"Debit","cleared":true,"category":"Gas & Fuel"},{"tranid":"9d2dfb00-5650-4fc2-ad2a-92c08d465a6f","description":"McDonald's","date":"2013-08-02","amount":"492","type":"Debit","cleared":true,"category":"Eating Out"},{"tranid":"4679ca82-092a-470f-907e-0aef628890a2","description":"Amazon (EWS)","date":"2013-08-03","amount":"85","type":"Debit","cleared":true,"category":"Subscriptions"},{"tranid":"0c278098-45bc-4690-8a7f-f4440e363f15","description":"Amazon","date":"2013-08-03","amount":"758","type":"Debit","cleared":true,"category":"Books and Supplies"},{"tranid":"98679900-d22d-4d45-bfb0-f4485c80b5af","description":"Azure Standard","date":"2013-07-26","amount":"22986","type":"Debit","cleared":true,"category":"Co-ops"},{"tranid":"d02f6030-8807-4548-99cb-c4717b885320","description":"Mobile Deposit","date":"2013-08-04","amount":"12251","type":"Credit","cleared":true,"category":"Reimbursement"},{"tranid":"2cf40d4c-b5ec-47d2-b22b-51f9035ab718","description":"Kohl's Card","date":"2013-08-06","amount":12651,"type":"Debit","cleared":true,"category":"Kohl's Card"},{"tranid":"5f296fe5-2c11-484a-84c6-a27d80d7156f","description":"DirecTV","date":"2013-08-06","amount":"10398","type":"Debit","cleared":true,"category":"TV Service"},{"tranid":"f5f82a92-4425-4673-bab4-0ff8c3de9d26","description":"City of Bloomington","date":"2013-08-06","amount":"13375","type":"Debit","cleared":true,"category":"Water Service"},{"tranid":"bcd8b3af-427c-4cdd-9d65-d5a180e81dd5","description":"Netflix","date":"2013-08-08","amount":799,"type":"Debit","cleared":true,"category":"Netflix"},{"tranid":"95013f0d-729f-43e8-8c01-dd81f5c4fdcb","description":"Barb Brown","date":"2013-08-05","amount":20000,"type":"Credit","cleared":true,"category":"Rental Income"},{"tranid":"c2672d4b-09b4-4c81-ab51-d6d6cdf4a7e0","description":"Wallgreens","date":"2013-08-05","amount":475,"type":"Debit","cleared":true,"category":"Doctor Bills"},{"tranid":"41b0c903-0d26-487b-9851-a5148c73abc5","description":"Old Route 66 Family Restaurant","date":"2013-08-05","amount":1758,"type":"Debit","cleared":true,"category":"Eating Out"},{"tranid":"332e2ad7-dfe2-40da-a46c-5a4902aaf2b3","description":"Transfer To Savings","date":"2013-08-06","amount":65000,"type":"Debit","cleared":true,"category":"Emergency Fund"},{"tranid":"faa60630-5f5f-4f97-9de1-a748b8236539","description":"Best Buy","date":"2013-08-09","amount":2998,"type":"Debit","cleared":true,"category":"Phone Insurance"},{"tranid":"ef24b133-f757-4ea5-afcc-6f7e91544567","description":"CILAC","date":"2013-08-09","amount":8200,"type":"Debit","cleared":true,"category":"CILAC"},{"tranid":"c4cbb380-4e84-4585-a79c-840c093e1ba2","description":"Amazon Chase","date":"2013-08-09","amount":7000,"type":"Debit","cleared":true,"category":"Amazon Chase"},{"tranid":"dd6354d3-08d2-4002-b409-dd0c4cab7fd9","description":"Home Depot","date":"2013-08-09","amount":8000,"type":"Debit","cleared":true,"category":"Home Depot (HTC)"},{"tranid":"b88a4892-ad97-4b5d-8075-b6571f7a472d","description":"IAA Credit Union","date":"2013-08-09","amount":8000,"type":"Debit","cleared":true,"category":"IAA Credit Union"},{"tranid":"0de0e972-030a-4ffd-b5e2-54f546229fff","description":"Meijier","date":"2013-08-07","amount":2024,"type":"Debit","cleared":true,"category":"Books and Supplies"},{"tranid":"df1c665b-b22b-4d4e-976b-639eed3d266f","description":"Meijer Gas","date":"2013-08-09","amount":4938,"type":"Debit","cleared":true,"category":"Gas & Fuel"},{"tranid":"ac241023-ed55-45ca-98a1-a6032e21b717","description":"Envelopes","date":"2013-08-09","amount":56500,"type":"Debit","cleared":true,"category":"Split","categories":[{"category":"Groceries","amount":"55000"},{"category":"Kid's Earnings","amount":"1500"}]},{"tranid":"98569369-6e74-43c7-9724-efa6bc8ca7f6","description":"State Farm Paycheck","date":"2013-08-09","amount":302547,"type":"Credit","cleared":true,"category":"1st Paycheck"},{"tranid":"d06a31c1-1b24-4659-95fc-3fa08bc0d70f","description":"Schwan's","date":"2013-08-09","amount":4909,"type":"Debit","cleared":true,"category":"Schwan's"},{"tranid":"e2d02089-d809-4e56-8fe2-4e54874e3391","description":"Chipotle","date":"2013-08-09","amount":1416,"type":"Debit","cleared":true,"category":"Eating Out"},{"tranid":"4ac56be7-f059-492c-a1f4-b8de78a7f731","description":"Dr. Gallo","date":"2013-08-09","amount":8000,"type":"Debit","cleared":true,"category":"Doctor Bills"},{"tranid":"2c162d77-53e6-491e-9861-dbe2f718827c","description":"Medical Hills Internists","date":"2013-08-09","amount":1130,"type":"Debit","cleared":true,"category":"Doctor Bills"},{"tranid":"fd870648-0de7-40f7-84ad-5088ef50e9af","description":"Frontier Communications","date":"2013-08-09","amount":8628,"type":"Debit","cleared":true,"category":"Phone Service"},{"tranid":"070ea59d-8dd7-4274-9c83-975de014bc78","description":"McDonalds","date":"2013-08-10","amount":492,"type":"Debit","cleared":true,"category":"Eating Out"},{"tranid":"0d867464-e311-48ef-bae5-6816963014fe","description":"Abigail Natenshon","date":"2013-08-12","amount":17500,"type":"Debit","cleared":true,"category":"Therapy"},{"tranid":"347ac7b8-efbd-44ff-9fa1-c964a8f4c037","description":"Campus Crusade","date":"2013-08-12","amount":1500,"type":"Debit","cleared":true,"category":"Charity"},{"tranid":"4150086e-4391-4534-bf7b-153638f5a080","description":"E-Free","date":"2013-08-12","amount":6000,"type":"Debit","cleared":true,"category":"Tithe"},{"tranid":"19ca4250-e1fc-4fa1-aee2-6363b7b5e9a9","description":"PNC Loan","date":"2013-08-12","amount":53417,"type":"Debit","cleared":true,"category":"2nd Mortgage"},{"tranid":"5977aafa-79f6-4602-8fcc-b3f42e667262","description":"State Farm Vending","date":"2013-08-12","amount":100,"type":"Debit","cleared":true,"category":"Eating Out"},{"tranid":"be75d329-58f5-4da7-aca8-3c258a5b00e3","description":"Amazon","date":"2013-08-12","amount":1209,"type":"Debit","cleared":true,"category":"Books and Supplies"},{"tranid":"0b953468-a9a0-4bf6-89bf-dac5860265ee","description":"Nicor Gas","date":"2013-08-14","amount":13679,"type":"Debit","cleared":true,"category":"Natural Gas"},{"tranid":"cb9341af-00a6-4b64-ad7a-6be2e1439456","description":"Amazon","date":"2013-08-14","amount":3461,"type":"Debit","cleared":true,"category":"Birthday"},{"tranid":"e75830d3-7bea-4ea6-9b00-112203cacbfd","description":"Cornbelt","date":"2013-08-14","amount":22200,"type":"Debit","cleared":true,"category":"Electrical Service"},{"tranid":"1e726beb-ddbd-468e-b7f8-593f0f327d36","description":"Deborah","date":"2013-08-15","amount":10500,"type":"Debit","cleared":true,"category":"Suppliments"},{"tranid":"2fd8d040-0597-43b0-8dc0-c3780dd4b6b7","description":"Align Life","date":"2013-08-15","amount":20500,"type":"Debit","cleared":true,"category":"Dr. Oliger"},{"tranid":"bbe233ff-a011-4a29-8a35-ff9b25186284","description":"Bloomington Radiology","date":"2013-08-15","amount":850,"type":"Debit","cleared":true,"category":"Doctor Bills"},{"tranid":"0bcedf20-8a03-4134-94d0-36ee3f23cf51","description":"Barb Brown","date":"2013-08-17","amount":20000,"type":"Credit","cleared":true,"category":"Rental Income"},{"tranid":"7c7dffc4-a443-42db-b366-19db257184b2","description":"Thorton's","date":"2013-08-17","amount":2651,"type":"Debit","cleared":true,"category":"Gas & Fuel"},{"tranid":"cda98d54-1b29-4b79-8080-d520c1186d57","description":"Netflix","date":"2013-08-18","amount":799,"type":"Debit","cleared":true,"category":"Netflix"},{"tranid":"aabc4058-6301-4426-911e-043fbabac434","description":"Barb Brown","date":"2013-08-19","amount":10000,"type":"Credit","cleared":true,"category":"Reimbursement"},{"tranid":"214d965e-6860-44de-91c6-a27946282d25","description":"Bloomington Radiology","date":"2013-08-19","amount":1200,"type":"Debit","cleared":true,"category":"Doctor Bills"},{"tranid":"8e715d26-8f56-4d05-80af-ea8c4c75e112","description":"iHome","date":"2013-08-20","amount":2500,"type":"Debit","cleared":true,"category":"Books and Supplies"},{"tranid":"5d36e70c-3ae1-4238-a15d-f450108f3c82","description":"Interest Payment","date":"2013-08-21","amount":2,"type":"Credit","cleared":true,"category":"Reimbursement"},{"tranid":"e9845e2c-b847-4dda-8672-13d1f8438af8","description":"Tonya - Birthday","date":"2013-08-21","amount":6000,"type":"Debit","cleared":true,"category":"Birthday"},{"tranid":"788a3e5d-494e-42c9-9e06-f10d8b1e5597","description":"Meijer","date":"2013-08-21","amount":492,"type":"Debit","cleared":true,"category":"Groceries"},{"tranid":"f806edb8-4792-4665-b225-3775de81260a","description":"Cornbelters","date":"2013-08-21","amount":1800,"type":"Debit","cleared":true,"category":"Eating Out"},{"tranid":"4085de39-cd0d-473b-a375-9b46df610cc1","description":"McLean County Eye Center","date":"2013-08-21","amount":11100,"type":"Debit","cleared":true,"category":"Doctor Bills"},{"tranid":"33176272-4e0c-4a33-9163-1f9886733ad4","description":"Kobe","date":"2013-08-22","amount":10318,"type":"Debit","cleared":true,"category":"Birthday"}]}